{ "indexes" : [ { "v" : 1, "key" : { "_id" : 1 }, "ns" : "wdts-0.edges", "name" : "_id_" }, { "v" : 1, "key" : { "a_node_id" : 1, "b_node_id" : 1 }, "unique" : true, "ns" : "wdts-0.edges", "name" : "a_node_id_1_b_node_id_1", "background" : true, "safe" : null }, { "v" : 1, "key" : { "meta.votes.user_id" : 1 }, "ns" : "wdts-0.edges", "name" : "meta.votes.user_id_1", "background" : true, "safe" : null }, { "v" : 1, "key" : { "meta.create_date" : 1 }, "ns" : "wdts-0.edges", "name" : "meta.create_date_1", "background" : true, "safe" : null }, { "v" : 1, "key" : { "b_node_id" : 1 }, "ns" : "wdts-0.edges", "name" : "b_node_id_1", "background" : true, "safe" : null }, { "v" : 1, "key" : { "meta.create_user_id" : 1 }, "ns" : "wdts-0.edges", "name" : "meta.create_user_id_1", "background" : true, "safe" : null } ] }